lastpass_aws_login/__init__.py
lastpass_aws_login/conf.py
lastpass_aws_login/credentials.py
lastpass_aws_login/exceptions.py
lastpass_aws_login/lastpass.py
lastpass_aws_login/main.py
lastpass_aws_login/utils.py
lastpass_aws_login-0.1.7.dist-info/LICENSE
lastpass_aws_login-0.1.7.dist-info/METADATA
lastpass_aws_login-0.1.7.dist-info/WHEEL
lastpass_aws_login-0.1.7.dist-info/entry_points.txt
lastpass_aws_login-0.1.7.dist-info/top_level.txt
lastpass_aws_login-0.1.7.dist-info/RECORD
