Metadata-Version: 2.1
Name: lastpass-aws-login
Version: 0.1.7
Summary: Tool for using AWS CLI with LastPass SAML
Home-page: https://github.com/NitorCreations/lastpass-aws-login
Author: Pasi Niemi
Author-email: pasi.niemi@nitor.com
License: GPLv3
Keywords: lastpass aws awscli boto3
Platform: UNKNOWN
Classifier: Environment :: Console
Classifier: Intended Audience :: Developers
Classifier: Intended Audience :: System Administrators
Classifier: License :: OSI Approved :: GNU General Public License v3 (GPLv3)
Classifier: Programming Language :: Python
Classifier: Programming Language :: Python :: 2
Classifier: Programming Language :: Python :: 2.7
Classifier: Programming Language :: Python :: 3
Classifier: Programming Language :: Python :: 3.6
Classifier: Programming Language :: Python :: 3.7
Requires-Dist: future
Requires-Dist: requests (>=2.22.0")
Requires-Dist: threadlocal-aws (>=0.10)
